__init__.py
corecfg/__init__.py
corecfg/multi_entity.py
corecfg/multi_entity_cli.py
corecfg-0.1.2.dist-info/LICENSE
corecfg-0.1.2.dist-info/METADATA
corecfg-0.1.2.dist-info/WHEEL
corecfg-0.1.2.dist-info/entry_points.txt
corecfg-0.1.2.dist-info/top_level.txt
corecfg-0.1.2.dist-info/RECORD
