Metadata-Version: 2.1
Name: corecfg
Version: 0.1.2
Summary: Core configuration classes to serve as a foundation (base class) for configuring various Python projects.
Author-email: Ed Waldner <waldevburry@proton.me>
Maintainer-email: Ed Waldner <waldevburry@proton.me>
Project-URL: Homepage, https://github.com/ew98/corecfg
Project-URL: Documentation, https://github.com/ew98/corecfg/wiki/CoreCfg
Project-URL: Issues, https://github.com/ew98/corecfg/issues
Keywords: util,utility
Classifier: Development Status :: 3 - Alpha
Classifier: Environment :: Console
Classifier: Intended Audience :: Developers
Classifier: License :: OSI Approved :: MIT License
Classifier: Natural Language :: English
Classifier: Programming Language :: Python :: 3.9
Classifier: Programming Language :: Python :: 3.10
Classifier: Programming Language :: Python :: 3.11
Classifier: Operating System :: OS Independent
Classifier: Topic :: Utilities
Requires-Python: >=3.9
License-File: LICENSE
Requires-Dist: argcomplete
Requires-Dist: quickcolor
Requires-Dist: showexception
